MANIFEST.in
README.md
README.rst
requirements.txt
setup.cfg
setup.py
easy_notifier/__init__.py
easy_notifier.egg-info/PKG-INFO
easy_notifier.egg-info/SOURCES.txt
easy_notifier.egg-info/dependency_links.txt
easy_notifier.egg-info/requires.txt
easy_notifier.egg-info/top_level.txt