Metadata-Version: 1.1
Name: easy-notifier
Version: 0.1.5
Summary: Notify when your process finished
Home-page: https://github.com/chie8842/easy_notifier
Author: Chie Hayashida
Author-email: chie-hayashida@cookpad.com
License: MIT
Platform: UNKNOWN
Classifier: Development Status :: 3 - Alpha
Classifier: Environment :: Console
Classifier: Intended Audience :: Developers
Classifier: License :: OSI Approved :: MIT License
Classifier: Operating System :: OS Independent
Classifier: Programming Language :: Python
Classifier: Programming Language :: Python :: 3
Classifier: Programming Language :: Python :: 3.5
Classifier: Programming Language :: Python :: 3.6
Classifier: Topic :: Software Development :: User Interfaces
